kroger/__init__.py
kroger/client.py
kroger/location.py
kroger/product.py
kroger/tests/__init__.py
kroger/tests/test_client.py
kroger/tests/test_location.py
kroger/tests/test_product.py
kroger_python-0.1.1.dist-info/licenses/LICENSE
kroger_python-0.1.1.dist-info/METADATA
kroger_python-0.1.1.dist-info/WHEEL
kroger_python-0.1.1.dist-info/top_level.txt
kroger_python-0.1.1.dist-info/RECORD
